CRM_tensorflow/__init__.py
CRM_tensorflow/crm_tensorflow.py
crm_tensorflow-0.1.6.dist-info/licenses/LICENSE
crm_tensorflow-0.1.6.dist-info/METADATA
crm_tensorflow-0.1.6.dist-info/WHEEL
crm_tensorflow-0.1.6.dist-info/top_level.txt
crm_tensorflow-0.1.6.dist-info/RECORD
