Metadata-Version: 2.4
Name: CRM_tensorflow
Version: 0.1.6
Summary: A non-official implementation of the Complex Ratio Mask (CRM) technique as a Tensorflow layer.
Home-page: https://github.com/narrietal/CRM_tensorflow
Author: Nicolas Arrieta Larraza
Author-email: n.arrieta.larraza@gmail.com
Classifier: Programming Language :: Python :: 3
Classifier: License :: OSI Approved :: MIT License
Classifier: Operating System :: OS Independent
Requires-Python: >=3.6
License-File: LICENSE
Requires-Dist: tensorflow>=2.0.0
Dynamic: author
Dynamic: author-email
Dynamic: classifier
Dynamic: description
Dynamic: description-content-type
Dynamic: home-page
Dynamic: license-file
Dynamic: requires-dist
Dynamic: requires-python
Dynamic: summary
